{
	"type": "qna",
	"id": "70",
	"content_type": "video",
	"property_keys": ["type", "id", "content_type"],
	"title": {
		"ru": "Сессия ответов и вопросов #70",
		"kk": "Сұрақ-жауап сессиясы #70",
		"en": "Questions & answers session #70"
	},
	"files_list": [
		{
			"path": "metadata.json",
			"type": "metadata",
			"lang": "en"
		},
		{
			"path": "video/ru/video.mp4",
			"type": "video",
			"lang": "ru"
		},
		{
			"path": "presentation/presentation.en.pptx",
			"type": "presentation",
			"lang": "en"
    },
    {
        "path": "chapters/chapters.en.vtt",
        "type": "chapters",
        "lang": "en"
    },
      {
        "path": "subtitles/subtitles.ru.vtt",
        "type": "subtitles",
        "lang": "ru"
    },
    {
        "path": "subtitles/subtitles.kk.vtt",
        "type": "subtitles",
        "lang": "kk"
    }
	]
}